sniffcat/__init__.py
sniffcat-0.1.8.dist-info/licenses/LICENSE
sniffcat-0.1.8.dist-info/METADATA
sniffcat-0.1.8.dist-info/WHEEL
sniffcat-0.1.8.dist-info/top_level.txt
sniffcat-0.1.8.dist-info/RECORD
