Metadata-Version: 2.4
Name: sniffcat
Version: 0.1.8
Summary: Python client for SniffCat API.
Home-page: https://github.com/yourusername/sniffcat.py
Author: Dominik 'skiop' S. <
Author-email: ntxg@proton.me
License: MIT
Requires-Python: >=3.8
License-File: LICENSE
Requires-Dist: requests
Dynamic: author
Dynamic: author-email
Dynamic: description
Dynamic: description-content-type
Dynamic: home-page
Dynamic: license
Dynamic: license-file
Dynamic: requires-dist
Dynamic: requires-python
Dynamic: summary
